<annotation>
	<folder>train</folder>
	<filename>27.png</filename>
	<path>/home/raycad/dev/projects/vintech/src/vfip-pocs/src/hmi_automation_testing/images/hmi_images/train/27.png</path>
	<source>
		<database>Unknown</database>
	</source>
	<size>
		<width>1337</width>
		<height>793</height>
		<depth>3</depth>
	</size>
	<segmented>0</segmented>
	<object>
		<name>bluetooth_on</name>
		<pose>Unspecified</pose>
		<truncated>0</truncated>
		<difficult>0</difficult>
		<bndbox>
			<xmin>150</xmin>
			<ymin>77</ymin>
			<xmax>189</xmax>
			<ymax>129</ymax>
		</bndbox>
	</object>
	<object>
		<name>braking_on</name>
		<pose>Unspecified</pose>
		<truncated>0</truncated>
		<difficult>0</difficult>
		<bndbox>
			<xmin>217</xmin>
			<ymin>79</ymin>
			<xmax>279</xmax>
			<ymax>126</ymax>
		</bndbox>
	</object>
	<object>
		<name>calling_on</name>
		<pose>Unspecified</pose>
		<truncated>0</truncated>
		<difficult>0</difficult>
		<bndbox>
			<xmin>317</xmin>
			<ymin>78</ymin>
			<xmax>369</xmax>
			<ymax>126</ymax>
		</bndbox>
	</object>
	<object>
		<name>sms_on</name>
		<pose>Unspecified</pose>
		<truncated>0</truncated>
		<difficult>0</difficult>
		<bndbox>
			<xmin>395</xmin>
			<ymin>77</ymin>
			<xmax>447</xmax>
			<ymax>122</ymax>
		</bndbox>
	</object>
	<object>
		<name>connection_lost</name>
		<pose>Unspecified</pose>
		<truncated>0</truncated>
		<difficult>0</difficult>
		<bndbox>
			<xmin>1131</xmin>
			<ymin>179</ymin>
			<xmax>1247</xmax>
			<ymax>268</ymax>
		</bndbox>
	</object>
	<object>
		<name>vin_id</name>
		<pose>Unspecified</pose>
		<truncated>0</truncated>
		<difficult>0</difficult>
		<bndbox>
			<xmin>1135</xmin>
			<ymin>403</ymin>
			<xmax>1247</xmax>
			<ymax>501</ymax>
		</bndbox>
	</object>
	<object>
		<name>error_code</name>
		<pose>Unspecified</pose>
		<truncated>0</truncated>
		<difficult>0</difficult>
		<bndbox>
			<xmin>951</xmin>
			<ymin>290</ymin>
			<xmax>1080</xmax>
			<ymax>379</ymax>
		</bndbox>
	</object>
	<object>
		<name>low_battery</name>
		<pose>Unspecified</pose>
		<truncated>0</truncated>
		<difficult>0</difficult>
		<bndbox>
			<xmin>94</xmin>
			<ymin>678</ymin>
			<xmax>170</xmax>
			<ymax>753</ymax>
		</bndbox>
	</object>
</annotation>
