<annotation>
	<folder>train</folder>
	<filename>59.png</filename>
	<path>/home/raycad/dev/projects/vintech/src/vfip-pocs/src/hmi_automation_testing/images/hmi_images/train/59.png</path>
	<source>
		<database>Unknown</database>
	</source>
	<size>
		<width>972</width>
		<height>702</height>
		<depth>3</depth>
	</size>
	<segmented>0</segmented>
	<object>
		<name>bluetooth_on</name>
		<pose>Unspecified</pose>
		<truncated>0</truncated>
		<difficult>0</difficult>
		<bndbox>
			<xmin>117</xmin>
			<ymin>129</ymin>
			<xmax>144</xmax>
			<ymax>165</ymax>
		</bndbox>
	</object>
	<object>
		<name>braking_on</name>
		<pose>Unspecified</pose>
		<truncated>0</truncated>
		<difficult>0</difficult>
		<bndbox>
			<xmin>163</xmin>
			<ymin>128</ymin>
			<xmax>211</xmax>
			<ymax>166</ymax>
		</bndbox>
	</object>
	<object>
		<name>calling_on</name>
		<pose>Unspecified</pose>
		<truncated>0</truncated>
		<difficult>0</difficult>
		<bndbox>
			<xmin>238</xmin>
			<ymin>130</ymin>
			<xmax>273</xmax>
			<ymax>164</ymax>
		</bndbox>
	</object>
	<object>
		<name>sms_on</name>
		<pose>Unspecified</pose>
		<truncated>0</truncated>
		<difficult>0</difficult>
		<bndbox>
			<xmin>293</xmin>
			<ymin>130</ymin>
			<xmax>331</xmax>
			<ymax>164</ymax>
		</bndbox>
	</object>
	<object>
		<name>connection_lost</name>
		<pose>Unspecified</pose>
		<truncated>0</truncated>
		<difficult>0</difficult>
		<bndbox>
			<xmin>809</xmin>
			<ymin>206</ymin>
			<xmax>891</xmax>
			<ymax>270</ymax>
		</bndbox>
	</object>
	<object>
		<name>vin_id</name>
		<pose>Unspecified</pose>
		<truncated>0</truncated>
		<difficult>0</difficult>
		<bndbox>
			<xmin>812</xmin>
			<ymin>362</ymin>
			<xmax>893</xmax>
			<ymax>430</ymax>
		</bndbox>
	</object>
	<object>
		<name>error_code</name>
		<pose>Unspecified</pose>
		<truncated>0</truncated>
		<difficult>0</difficult>
		<bndbox>
			<xmin>685</xmin>
			<ymin>282</ymin>
			<xmax>774</xmax>
			<ymax>346</ymax>
		</bndbox>
	</object>
	<object>
		<name>low_battery</name>
		<pose>Unspecified</pose>
		<truncated>0</truncated>
		<difficult>0</difficult>
		<bndbox>
			<xmin>68</xmin>
			<ymin>560</ymin>
			<xmax>124</xmax>
			<ymax>611</ymax>
		</bndbox>
	</object>
</annotation>
